astroimtools/__init__.py
astroimtools/_astropy_init.py
astroimtools/arithmetic.py
astroimtools/conftest.py
astroimtools/cutout_tools.py
astroimtools/filtering.py
astroimtools/nddata_adapters.py
astroimtools/stats.py
astroimtools/utils.py
astroimtools/version.py
astroimtools/scripts/__init__.py
astroimtools/scripts/imarith.py
astroimtools/scripts/imstats.py
astroimtools/tests/__init__.py
astroimtools/tests/test_arithmetic.py
astroimtools/tests/test_filtering.py
astroimtools/tests/test_stats.py
astroimtools/tests/test_utils.py
astroimtools-0.4.0.dist-info/LICENSE.rst
astroimtools-0.4.0.dist-info/METADATA
astroimtools-0.4.0.dist-info/WHEEL
astroimtools-0.4.0.dist-info/entry_points.txt
astroimtools-0.4.0.dist-info/top_level.txt
astroimtools-0.4.0.dist-info/RECORD
