Metadata-Version: 2.1
Name: astroimtools
Version: 0.4.0
Summary: Astronomical Image Tools
Author-email: Astroimtools Developers <help@stsci.edu>
License: Copyright (c) 2015, Association of Universities for Research in Astronomy (AURA)
Project-URL: homepage, https://github.com/spacetelescope/astroimtools
Project-URL: documentation, https://astroimtools.readthedocs.io/en/stable/
Keywords: astronomy,astrophysics,images,cutouts,statistics,filtering
Classifier: Intended Audience :: Science/Research
Classifier: License :: OSI Approved :: BSD License
Classifier: Natural Language :: English
Classifier: Operating System :: OS Independent
Classifier: Programming Language :: Python
Classifier: Programming Language :: Python :: 3
Classifier: Topic :: Scientific/Engineering :: Astronomy
Requires-Python: >=3.9
License-File: LICENSE.rst
Requires-Dist: numpy >=1.22
Requires-Dist: astropy >=5.0
Requires-Dist: scipy >=1.7.2
Provides-Extra: all
Requires-Dist: matplotlib >=3.5 ; extra == 'all'
Requires-Dist: photutils >=1.5 ; extra == 'all'
Requires-Dist: reproject >=0.9 ; extra == 'all'
Provides-Extra: docs
Requires-Dist: astroimtools[all] ; extra == 'docs'
Requires-Dist: ipython ; extra == 'docs'
Requires-Dist: nbsphinx ; extra == 'docs'
Requires-Dist: sphinx ; extra == 'docs'
Requires-Dist: sphinx-astropy >=1.6 ; extra == 'docs'
Requires-Dist: tomli ; (python_version < "3.11") and extra == 'docs'
Provides-Extra: test
Requires-Dist: pytest-astropy >=0.10 ; extra == 'test'
